{
  "Province_State": "",
  "Country": "Austria",
  "Latitude": "47.5162",
  "Longitude": "14.5501",
  "Category": "Recovered",
  "Data": [
    {
      "Item1": "2020-01-22T00:00:00",
      "Item2": 0.0
    },
    {
      "Item1": "2020-01-23T00:00:00",
      "Item2": 0.0
    },
    {
      "Item1": "2020-01-24T00:00:00",
      "Item2": 0.0
    },
    {
      "Item1": "2020-01-25T00:00:00",
      "Item2": 0.0
    },
    {
      "Item1": "2020-01-26T00:00:00",
      "Item2": 0.0
    },
    {
      "Item1": "2020-01-27T00:00:00",
      "Item2": 0.0
    },
    {
      "Item1": "2020-01-28T00:00:00",
      "Item2": 0.0
    },
    {
      "Item1": "2020-01-29T00:00:00",
      "Item2": 0.0
    },
    {
      "Item1": "2020-01-30T00:00:00",
      "Item2": 0.0
    },
    {
      "Item1": "2020-01-31T00:00:00",
      "Item2": 0.0
    },
    {
      "Item1": "2020-02-01T00:00:00",
      "Item2": 0.0
    },
    {
      "Item1": "2020-02-02T00:00:00",
      "Item2": 0.0
    },
    {
      "Item1": "2020-02-03T00:00:00",
      "Item2": 0.0
    },
    {
      "Item1": "2020-02-04T00:00:00",
      "Item2": 0.0
    },
    {
      "Item1": "2020-02-05T00:00:00",
      "Item2": 0.0
    },
    {
      "Item1": "2020-02-06T00:00:00",
      "Item2": 0.0
    },
    {
      "Item1": "2020-02-07T00:00:00",
      "Item2": 0.0
    },
    {
      "Item1": "2020-02-08T00:00:00",
      "Item2": 0.0
    },
    {
      "Item1": "2020-02-09T00:00:00",
      "Item2": 0.0
    },
    {
      "Item1": "2020-02-10T00:00:00",
      "Item2": 0.0
    },
    {
      "Item1": "2020-02-11T00:00:00",
      "Item2": 0.0
    },
    {
      "Item1": "2020-02-12T00:00:00",
      "Item2": 0.0
    },
    {
      "Item1": "2020-02-13T00:00:00",
      "Item2": 0.0
    },
    {
      "Item1": "2020-02-14T00:00:00",
      "Item2": 0.0
    },
    {
      "Item1": "2020-02-15T00:00:00",
      "Item2": 0.0
    },
    {
      "Item1": "2020-02-16T00:00:00",
      "Item2": 0.0
    },
    {
      "Item1": "2020-02-17T00:00:00",
      "Item2": 0.0
    },
    {
      "Item1": "2020-02-18T00:00:00",
      "Item2": 0.0
    },
    {
      "Item1": "2020-02-19T00:00:00",
      "Item2": 0.0
    },
    {
      "Item1": "2020-02-20T00:00:00",
      "Item2": 0.0
    },
    {
      "Item1": "2020-02-21T00:00:00",
      "Item2": 0.0
    },
    {
      "Item1": "2020-02-22T00:00:00",
      "Item2": 0.0
    },
    {
      "Item1": "2020-02-23T00:00:00",
      "Item2": 0.0
    },
    {
      "Item1": "2020-02-24T00:00:00",
      "Item2": 0.0
    },
    {
      "Item1": "2020-02-25T00:00:00",
      "Item2": 0.0
    },
    {
      "Item1": "2020-02-26T00:00:00",
      "Item2": 0.0
    },
    {
      "Item1": "2020-02-27T00:00:00",
      "Item2": 0.0
    },
    {
      "Item1": "2020-02-28T00:00:00",
      "Item2": 0.0
    },
    {
      "Item1": "2020-02-29T00:00:00",
      "Item2": 0.0
    },
    {
      "Item1": "2020-03-01T00:00:00",
      "Item2": 0.0
    },
    {
      "Item1": "2020-03-02T00:00:00",
      "Item2": 0.0
    },
    {
      "Item1": "2020-03-03T00:00:00",
      "Item2": 0.0
    },
    {
      "Item1": "2020-03-04T00:00:00",
      "Item2": 0.0
    },
    {
      "Item1": "2020-03-05T00:00:00",
      "Item2": 0.0
    },
    {
      "Item1": "2020-03-06T00:00:00",
      "Item2": 0.0
    },
    {
      "Item1": "2020-03-07T00:00:00",
      "Item2": 0.0
    },
    {
      "Item1": "2020-03-08T00:00:00",
      "Item2": 0.0
    },
    {
      "Item1": "2020-03-09T00:00:00",
      "Item2": 2.0
    },
    {
      "Item1": "2020-03-10T00:00:00",
      "Item2": 4.0
    },
    {
      "Item1": "2020-03-11T00:00:00",
      "Item2": 4.0
    },
    {
      "Item1": "2020-03-12T00:00:00",
      "Item2": 4.0
    },
    {
      "Item1": "2020-03-13T00:00:00",
      "Item2": 6.0
    },
    {
      "Item1": "2020-03-14T00:00:00",
      "Item2": 6.0
    },
    {
      "Item1": "2020-03-15T00:00:00",
      "Item2": 6.0
    },
    {
      "Item1": "2020-03-16T00:00:00",
      "Item2": 6.0
    },
    {
      "Item1": "2020-03-17T00:00:00",
      "Item2": 1.0
    },
    {
      "Item1": "2020-03-18T00:00:00",
      "Item2": 9.0
    },
    {
      "Item1": "2020-03-19T00:00:00",
      "Item2": 9.0
    },
    {
      "Item1": "2020-03-20T00:00:00",
      "Item2": 9.0
    },
    {
      "Item1": "2020-03-21T00:00:00",
      "Item2": 9.0
    },
    {
      "Item1": "2020-03-22T00:00:00",
      "Item2": 9.0
    },
    {
      "Item1": "2020-03-23T00:00:00",
      "Item2": 9.0
    },
    {
      "Item1": "2020-03-24T00:00:00",
      "Item2": 9.0
    },
    {
      "Item1": "2020-03-25T00:00:00",
      "Item2": 9.0
    },
    {
      "Item1": "2020-03-26T00:00:00",
      "Item2": 112.0
    },
    {
      "Item1": "2020-03-27T00:00:00",
      "Item2": 225.0
    },
    {
      "Item1": "2020-03-28T00:00:00",
      "Item2": 225.0
    },
    {
      "Item1": "2020-03-29T00:00:00",
      "Item2": 479.0
    },
    {
      "Item1": "2020-03-30T00:00:00",
      "Item2": 636.0
    },
    {
      "Item1": "2020-03-31T00:00:00",
      "Item2": 1095.0
    },
    {
      "Item1": "2020-04-01T00:00:00",
      "Item2": 1436.0
    },
    {
      "Item1": "2020-04-02T00:00:00",
      "Item2": 1749.0
    },
    {
      "Item1": "2020-04-03T00:00:00",
      "Item2": 2022.0
    },
    {
      "Item1": "2020-04-04T00:00:00",
      "Item2": 2507.0
    },
    {
      "Item1": "2020-04-05T00:00:00",
      "Item2": 2998.0
    },
    {
      "Item1": "2020-04-06T00:00:00",
      "Item2": 3463.0
    },
    {
      "Item1": "2020-04-07T00:00:00",
      "Item2": 4046.0
    },
    {
      "Item1": "2020-04-08T00:00:00",
      "Item2": 4512.0
    },
    {
      "Item1": "2020-04-09T00:00:00",
      "Item2": 5240.0
    },
    {
      "Item1": "2020-04-10T00:00:00",
      "Item2": 6064.0
    },
    {
      "Item1": "2020-04-11T00:00:00",
      "Item2": 6604.0
    },
    {
      "Item1": "2020-04-12T00:00:00",
      "Item2": 6987.0
    },
    {
      "Item1": "2020-04-13T00:00:00",
      "Item2": 7343.0
    },
    {
      "Item1": "2020-04-14T00:00:00",
      "Item2": 7633.0
    },
    {
      "Item1": "2020-04-15T00:00:00",
      "Item2": 8098.0
    },
    {
      "Item1": "2020-04-16T00:00:00",
      "Item2": 8986.0
    },
    {
      "Item1": "2020-04-17T00:00:00",
      "Item2": 9704.0
    },
    {
      "Item1": "2020-04-18T00:00:00",
      "Item2": 10214.0
    },
    {
      "Item1": "2020-04-19T00:00:00",
      "Item2": 10501.0
    },
    {
      "Item1": "2020-04-20T00:00:00",
      "Item2": 10631.0
    },
    {
      "Item1": "2020-04-21T00:00:00",
      "Item2": 10971.0
    },
    {
      "Item1": "2020-04-22T00:00:00",
      "Item2": 11328.0
    },
    {
      "Item1": "2020-04-23T00:00:00",
      "Item2": 11694.0
    },
    {
      "Item1": "2020-04-24T00:00:00",
      "Item2": 11872.0
    },
    {
      "Item1": "2020-04-25T00:00:00",
      "Item2": 12103.0
    },
    {
      "Item1": "2020-04-26T00:00:00",
      "Item2": 12282.0
    },
    {
      "Item1": "2020-04-27T00:00:00",
      "Item2": 12362.0
    },
    {
      "Item1": "2020-04-28T00:00:00",
      "Item2": 12580.0
    },
    {
      "Item1": "2020-04-29T00:00:00",
      "Item2": 12779.0
    },
    {
      "Item1": "2020-04-30T00:00:00",
      "Item2": 12907.0
    },
    {
      "Item1": "2020-05-01T00:00:00",
      "Item2": 13110.0
    },
    {
      "Item1": "2020-05-02T00:00:00",
      "Item2": 13180.0
    },
    {
      "Item1": "2020-05-03T00:00:00",
      "Item2": 13228.0
    },
    {
      "Item1": "2020-05-04T00:00:00",
      "Item2": 13316.0
    },
    {
      "Item1": "2020-05-05T00:00:00",
      "Item2": 13462.0
    },
    {
      "Item1": "2020-05-06T00:00:00",
      "Item2": 13639.0
    },
    {
      "Item1": "2020-05-07T00:00:00",
      "Item2": 13698.0
    },
    {
      "Item1": "2020-05-08T00:00:00",
      "Item2": 13836.0
    },
    {
      "Item1": "2020-05-09T00:00:00",
      "Item2": 13928.0
    },
    {
      "Item1": "2020-05-10T00:00:00",
      "Item2": 13991.0
    },
    {
      "Item1": "2020-05-11T00:00:00",
      "Item2": 14061.0
    },
    {
      "Item1": "2020-05-12T00:00:00",
      "Item2": 14148.0
    },
    {
      "Item1": "2020-05-13T00:00:00",
      "Item2": 14304.0
    },
    {
      "Item1": "2020-05-14T00:00:00",
      "Item2": 14405.0
    },
    {
      "Item1": "2020-05-15T00:00:00",
      "Item2": 14471.0
    },
    {
      "Item1": "2020-05-16T00:00:00",
      "Item2": 14524.0
    },
    {
      "Item1": "2020-05-17T00:00:00",
      "Item2": 14563.0
    },
    {
      "Item1": "2020-05-18T00:00:00",
      "Item2": 14614.0
    },
    {
      "Item1": "2020-05-19T00:00:00",
      "Item2": 14678.0
    },
    {
      "Item1": "2020-05-20T00:00:00",
      "Item2": 14882.0
    },
    {
      "Item1": "2020-05-21T00:00:00",
      "Item2": 14951.0
    },
    {
      "Item1": "2020-05-22T00:00:00",
      "Item2": 15005.0
    },
    {
      "Item1": "2020-05-23T00:00:00",
      "Item2": 15037.0
    },
    {
      "Item1": "2020-05-24T00:00:00",
      "Item2": 15063.0
    },
    {
      "Item1": "2020-05-25T00:00:00",
      "Item2": 15138.0
    },
    {
      "Item1": "2020-05-26T00:00:00",
      "Item2": 15182.0
    },
    {
      "Item1": "2020-05-27T00:00:00",
      "Item2": 15228.0
    },
    {
      "Item1": "2020-05-28T00:00:00",
      "Item2": 15286.0
    },
    {
      "Item1": "2020-05-29T00:00:00",
      "Item2": 15347.0
    },
    {
      "Item1": "2020-05-30T00:00:00",
      "Item2": 15520.0
    },
    {
      "Item1": "2020-05-31T00:00:00",
      "Item2": 15593.0
    },
    {
      "Item1": "2020-06-01T00:00:00",
      "Item2": 15596.0
    },
    {
      "Item1": "2020-06-02T00:00:00",
      "Item2": 15629.0
    },
    {
      "Item1": "2020-06-03T00:00:00",
      "Item2": 15672.0
    },
    {
      "Item1": "2020-06-04T00:00:00",
      "Item2": 15717.0
    },
    {
      "Item1": "2020-06-05T00:00:00",
      "Item2": 15742.0
    },
    {
      "Item1": "2020-06-06T00:00:00",
      "Item2": 15789.0
    },
    {
      "Item1": "2020-06-07T00:00:00",
      "Item2": 15793.0
    },
    {
      "Item1": "2020-06-08T00:00:00",
      "Item2": 15839.0
    },
    {
      "Item1": "2020-06-09T00:00:00",
      "Item2": 15875.0
    },
    {
      "Item1": "2020-06-10T00:00:00",
      "Item2": 15910.0
    },
    {
      "Item1": "2020-06-11T00:00:00",
      "Item2": 15949.0
    },
    {
      "Item1": "2020-06-12T00:00:00",
      "Item2": 15985.0
    },
    {
      "Item1": "2020-06-13T00:00:00",
      "Item2": 16012.0
    },
    {
      "Item1": "2020-06-14T00:00:00",
      "Item2": 16059.0
    },
    {
      "Item1": "2020-06-15T00:00:00",
      "Item2": 16066.0
    },
    {
      "Item1": "2020-06-16T00:00:00",
      "Item2": 16089.0
    },
    {
      "Item1": "2020-06-17T00:00:00",
      "Item2": 16099.0
    },
    {
      "Item1": "2020-06-18T00:00:00",
      "Item2": 16101.0
    },
    {
      "Item1": "2020-06-19T00:00:00",
      "Item2": 16141.0
    },
    {
      "Item1": "2020-06-20T00:00:00",
      "Item2": 16175.0
    },
    {
      "Item1": "2020-06-21T00:00:00",
      "Item2": 16197.0
    },
    {
      "Item1": "2020-06-22T00:00:00",
      "Item2": 16241.0
    },
    {
      "Item1": "2020-06-23T00:00:00",
      "Item2": 16261.0
    },
    {
      "Item1": "2020-06-24T00:00:00",
      "Item2": 16282.0
    },
    {
      "Item1": "2020-06-25T00:00:00",
      "Item2": 16320.0
    },
    {
      "Item1": "2020-06-26T00:00:00",
      "Item2": 16348.0
    },
    {
      "Item1": "2020-06-27T00:00:00",
      "Item2": 16371.0
    },
    {
      "Item1": "2020-06-28T00:00:00",
      "Item2": 16401.0
    },
    {
      "Item1": "2020-06-29T00:00:00",
      "Item2": 16420.0
    },
    {
      "Item1": "2020-06-30T00:00:00",
      "Item2": 16478.0
    },
    {
      "Item1": "2020-07-01T00:00:00",
      "Item2": 16491.0
    },
    {
      "Item1": "2020-07-02T00:00:00",
      "Item2": 16514.0
    },
    {
      "Item1": "2020-07-03T00:00:00",
      "Item2": 16558.0
    },
    {
      "Item1": "2020-07-04T00:00:00",
      "Item2": 16607.0
    },
    {
      "Item1": "2020-07-05T00:00:00",
      "Item2": 16615.0
    },
    {
      "Item1": "2020-07-06T00:00:00",
      "Item2": 16647.0
    },
    {
      "Item1": "2020-07-07T00:00:00",
      "Item2": 16686.0
    },
    {
      "Item1": "2020-07-08T00:00:00",
      "Item2": 16721.0
    },
    {
      "Item1": "2020-07-09T00:00:00",
      "Item2": 16758.0
    },
    {
      "Item1": "2020-07-10T00:00:00",
      "Item2": 16808.0
    },
    {
      "Item1": "2020-07-11T00:00:00",
      "Item2": 16864.0
    },
    {
      "Item1": "2020-07-12T00:00:00",
      "Item2": 16952.0
    },
    {
      "Item1": "2020-07-13T00:00:00",
      "Item2": 17000.0
    },
    {
      "Item1": "2020-07-14T00:00:00",
      "Item2": 17073.0
    },
    {
      "Item1": "2020-07-15T00:00:00",
      "Item2": 17175.0
    },
    {
      "Item1": "2020-07-16T00:00:00",
      "Item2": 17244.0
    },
    {
      "Item1": "2020-07-17T00:00:00",
      "Item2": 17335.0
    },
    {
      "Item1": "2020-07-18T00:00:00",
      "Item2": 17501.0
    },
    {
      "Item1": "2020-07-19T00:00:00",
      "Item2": 17599.0
    },
    {
      "Item1": "2020-07-20T00:00:00",
      "Item2": 17659.0
    },
    {
      "Item1": "2020-07-21T00:00:00",
      "Item2": 17716.0
    },
    {
      "Item1": "2020-07-22T00:00:00",
      "Item2": 17849.0
    },
    {
      "Item1": "2020-07-23T00:00:00",
      "Item2": 17943.0
    },
    {
      "Item1": "2020-07-24T00:00:00",
      "Item2": 18042.0
    },
    {
      "Item1": "2020-07-25T00:00:00",
      "Item2": 18124.0
    },
    {
      "Item1": "2020-07-26T00:00:00",
      "Item2": 18209.0
    },
    {
      "Item1": "2020-07-27T00:00:00",
      "Item2": 18246.0
    },
    {
      "Item1": "2020-07-28T00:00:00",
      "Item2": 18379.0
    },
    {
      "Item1": "2020-07-29T00:00:00",
      "Item2": 18528.0
    },
    {
      "Item1": "2020-07-30T00:00:00",
      "Item2": 18628.0
    },
    {
      "Item1": "2020-07-31T00:00:00",
      "Item2": 18758.0
    },
    {
      "Item1": "2020-08-01T00:00:00",
      "Item2": 18911.0
    },
    {
      "Item1": "2020-08-02T00:00:00",
      "Item2": 18984.0
    },
    {
      "Item1": "2020-08-03T00:00:00",
      "Item2": 19063.0
    },
    {
      "Item1": "2020-08-04T00:00:00",
      "Item2": 19336.0
    },
    {
      "Item1": "2020-08-05T00:00:00",
      "Item2": 19464.0
    },
    {
      "Item1": "2020-08-06T00:00:00",
      "Item2": 19596.0
    },
    {
      "Item1": "2020-08-07T00:00:00",
      "Item2": 19690.0
    },
    {
      "Item1": "2020-08-08T00:00:00",
      "Item2": 19812.0
    },
    {
      "Item1": "2020-08-09T00:00:00",
      "Item2": 19923.0
    },
    {
      "Item1": "2020-08-10T00:00:00",
      "Item2": 20010.0
    },
    {
      "Item1": "2020-08-11T00:00:00",
      "Item2": 20123.0
    },
    {
      "Item1": "2020-08-12T00:00:00",
      "Item2": 20268.0
    },
    {
      "Item1": "2020-08-13T00:00:00",
      "Item2": 20346.0
    },
    {
      "Item1": "2020-08-14T00:00:00",
      "Item2": 20499.0
    },
    {
      "Item1": "2020-08-15T00:00:00",
      "Item2": 20627.0
    },
    {
      "Item1": "2020-08-16T00:00:00",
      "Item2": 20681.0
    },
    {
      "Item1": "2020-08-17T00:00:00",
      "Item2": 20765.0
    },
    {
      "Item1": "2020-08-18T00:00:00",
      "Item2": 20870.0
    },
    {
      "Item1": "2020-08-19T00:00:00",
      "Item2": 20958.0
    },
    {
      "Item1": "2020-08-20T00:00:00",
      "Item2": 21093.0
    },
    {
      "Item1": "2020-08-21T00:00:00",
      "Item2": 21260.0
    },
    {
      "Item1": "2020-08-22T00:00:00",
      "Item2": 21406.0
    },
    {
      "Item1": "2020-08-23T00:00:00",
      "Item2": 21558.0
    },
    {
      "Item1": "2020-08-24T00:00:00",
      "Item2": 21657.0
    },
    {
      "Item1": "2020-08-25T00:00:00",
      "Item2": 21888.0
    },
    {
      "Item1": "2020-08-26T00:00:00",
      "Item2": 22145.0
    },
    {
      "Item1": "2020-08-27T00:00:00",
      "Item2": 22317.0
    },
    {
      "Item1": "2020-08-28T00:00:00",
      "Item2": 22594.0
    },
    {
      "Item1": "2020-08-29T00:00:00",
      "Item2": 22866.0
    },
    {
      "Item1": "2020-08-30T00:00:00",
      "Item2": 23070.0
    },
    {
      "Item1": "2020-08-31T00:00:00",
      "Item2": 23226.0
    },
    {
      "Item1": "2020-09-01T00:00:00",
      "Item2": 23565.0
    },
    {
      "Item1": "2020-09-02T00:00:00",
      "Item2": 23820.0
    },
    {
      "Item1": "2020-09-03T00:00:00",
      "Item2": 24171.0
    },
    {
      "Item1": "2020-09-04T00:00:00",
      "Item2": 24513.0
    },
    {
      "Item1": "2020-09-05T00:00:00",
      "Item2": 24828.0
    },
    {
      "Item1": "2020-09-06T00:00:00",
      "Item2": 25043.0
    },
    {
      "Item1": "2020-09-07T00:00:00",
      "Item2": 25300.0
    },
    {
      "Item1": "2020-09-08T00:00:00",
      "Item2": 25629.0
    },
    {
      "Item1": "2020-09-09T00:00:00",
      "Item2": 25764.0
    },
    {
      "Item1": "2020-09-10T00:00:00",
      "Item2": 26043.0
    },
    {
      "Item1": "2020-09-11T00:00:00",
      "Item2": 26257.0
    },
    {
      "Item1": "2020-09-12T00:00:00",
      "Item2": 26579.0
    },
    {
      "Item1": "2020-09-13T00:00:00",
      "Item2": 26760.0
    },
    {
      "Item1": "2020-09-14T00:00:00",
      "Item2": 27010.0
    },
    {
      "Item1": "2020-09-15T00:00:00",
      "Item2": 27354.0
    },
    {
      "Item1": "2020-09-16T00:00:00",
      "Item2": 27655.0
    },
    {
      "Item1": "2020-09-17T00:00:00",
      "Item2": 28044.0
    },
    {
      "Item1": "2020-09-18T00:00:00",
      "Item2": 28451.0
    },
    {
      "Item1": "2020-09-19T00:00:00",
      "Item2": 28961.0
    },
    {
      "Item1": "2020-09-20T00:00:00",
      "Item2": 29229.0
    },
    {
      "Item1": "2020-09-21T00:00:00",
      "Item2": 29516.0
    },
    {
      "Item1": "2020-09-22T00:00:00",
      "Item2": 30312.0
    },
    {
      "Item1": "2020-09-23T00:00:00",
      "Item2": 30949.0
    },
    {
      "Item1": "2020-09-24T00:00:00",
      "Item2": 31661.0
    },
    {
      "Item1": "2020-09-25T00:00:00",
      "Item2": 32301.0
    },
    {
      "Item1": "2020-09-26T00:00:00",
      "Item2": 33154.0
    },
    {
      "Item1": "2020-09-27T00:00:00",
      "Item2": 33589.0
    },
    {
      "Item1": "2020-09-28T00:00:00",
      "Item2": 34052.0
    },
    {
      "Item1": "2020-09-29T00:00:00",
      "Item2": 34916.0
    },
    {
      "Item1": "2020-09-30T00:00:00",
      "Item2": 35644.0
    },
    {
      "Item1": "2020-10-01T00:00:00",
      "Item2": 36476.0
    },
    {
      "Item1": "2020-10-02T00:00:00",
      "Item2": 37186.0
    },
    {
      "Item1": "2020-10-03T00:00:00",
      "Item2": 38045.0
    },
    {
      "Item1": "2020-10-04T00:00:00",
      "Item2": 38629.0
    },
    {
      "Item1": "2020-10-05T00:00:00",
      "Item2": 39058.0
    },
    {
      "Item1": "2020-10-06T00:00:00",
      "Item2": 39790.0
    },
    {
      "Item1": "2020-10-07T00:00:00",
      "Item2": 40499.0
    },
    {
      "Item1": "2020-10-08T00:00:00",
      "Item2": 41289.0
    },
    {
      "Item1": "2020-10-09T00:00:00",
      "Item2": 42039.0
    },
    {
      "Item1": "2020-10-10T00:00:00",
      "Item2": 42829.0
    },
    {
      "Item1": "2020-10-11T00:00:00",
      "Item2": 43448.0
    },
    {
      "Item1": "2020-10-12T00:00:00",
      "Item2": 44065.0
    },
    {
      "Item1": "2020-10-13T00:00:00",
      "Item2": 44949.0
    },
    {
      "Item1": "2020-10-14T00:00:00",
      "Item2": 45846.0
    },
    {
      "Item1": "2020-10-15T00:00:00",
      "Item2": 46798.0
    },
    {
      "Item1": "2020-10-16T00:00:00",
      "Item2": 47618.0
    },
    {
      "Item1": "2020-10-17T00:00:00",
      "Item2": 48771.0
    },
    {
      "Item1": "2020-10-18T00:00:00",
      "Item2": 49561.0
    },
    {
      "Item1": "2020-10-19T00:00:00",
      "Item2": 50359.0
    },
    {
      "Item1": "2020-10-20T00:00:00",
      "Item2": 51407.0
    },
    {
      "Item1": "2020-10-21T00:00:00",
      "Item2": 52617.0
    },
    {
      "Item1": "2020-10-22T00:00:00",
      "Item2": 53970.0
    },
    {
      "Item1": "2020-10-23T00:00:00",
      "Item2": 55195.0
    },
    {
      "Item1": "2020-10-24T00:00:00",
      "Item2": 56791.0
    },
    {
      "Item1": "2020-10-25T00:00:00",
      "Item2": 57858.0
    },
    {
      "Item1": "2020-10-26T00:00:00",
      "Item2": 59036.0
    },
    {
      "Item1": "2020-10-27T00:00:00",
      "Item2": 60308.0
    },
    {
      "Item1": "2020-10-28T00:00:00",
      "Item2": 61684.0
    },
    {
      "Item1": "2020-10-29T00:00:00",
      "Item2": 63366.0
    },
    {
      "Item1": "2020-10-30T00:00:00",
      "Item2": 64987.0
    },
    {
      "Item1": "2020-10-31T00:00:00",
      "Item2": 67226.0
    },
    {
      "Item1": "2020-11-01T00:00:00",
      "Item2": 69336.0
    },
    {
      "Item1": "2020-11-02T00:00:00",
      "Item2": 71691.0
    },
    {
      "Item1": "2020-11-03T00:00:00",
      "Item2": 74292.0
    },
    {
      "Item1": "2020-11-04T00:00:00",
      "Item2": 77036.0
    },
    {
      "Item1": "2020-11-05T00:00:00",
      "Item2": 80604.0
    },
    {
      "Item1": "2020-11-06T00:00:00",
      "Item2": 83707.0
    },
    {
      "Item1": "2020-11-07T00:00:00",
      "Item2": 88273.0
    },
    {
      "Item1": "2020-11-08T00:00:00",
      "Item2": 91719.0
    },
    {
      "Item1": "2020-11-09T00:00:00",
      "Item2": 94627.0
    },
    {
      "Item1": "2020-11-10T00:00:00",
      "Item2": 98663.0
    },
    {
      "Item1": "2020-11-11T00:00:00",
      "Item2": 103759.0
    },
    {
      "Item1": "2020-11-12T00:00:00",
      "Item2": 107875.0
    },
    {
      "Item1": "2020-11-13T00:00:00",
      "Item2": 112728.0
    },
    {
      "Item1": "2020-11-14T00:00:00",
      "Item2": 119415.0
    },
    {
      "Item1": "2020-11-15T00:00:00",
      "Item2": 125674.0
    },
    {
      "Item1": "2020-11-16T00:00:00",
      "Item2": 129671.0
    },
    {
      "Item1": "2020-11-17T00:00:00",
      "Item2": 136487.0
    },
    {
      "Item1": "2020-11-18T00:00:00",
      "Item2": 142738.0
    },
    {
      "Item1": "2020-11-19T00:00:00",
      "Item2": 149541.0
    },
    {
      "Item1": "2020-11-20T00:00:00",
      "Item2": 156483.0
    },
    {
      "Item1": "2020-11-21T00:00:00",
      "Item2": 162751.0
    },
    {
      "Item1": "2020-11-22T00:00:00",
      "Item2": 169260.0
    },
    {
      "Item1": "2020-11-23T00:00:00",
      "Item2": 175527.0
    },
    {
      "Item1": "2020-11-24T00:00:00",
      "Item2": 182620.0
    },
    {
      "Item1": "2020-11-25T00:00:00",
      "Item2": 189059.0
    },
    {
      "Item1": "2020-11-26T00:00:00",
      "Item2": 196342.0
    },
    {
      "Item1": "2020-11-27T00:00:00",
      "Item2": 203251.0
    },
    {
      "Item1": "2020-11-28T00:00:00",
      "Item2": 210697.0
    },
    {
      "Item1": "2020-11-29T00:00:00",
      "Item2": 216998.0
    },
    {
      "Item1": "2020-11-30T00:00:00",
      "Item2": 221692.0
    },
    {
      "Item1": "2020-12-01T00:00:00",
      "Item2": 227497.0
    },
    {
      "Item1": "2020-12-02T00:00:00",
      "Item2": 233657.0
    },
    {
      "Item1": "2020-12-03T00:00:00",
      "Item2": 238127.0
    },
    {
      "Item1": "2020-12-04T00:00:00",
      "Item2": 243775.0
    },
    {
      "Item1": "2020-12-05T00:00:00",
      "Item2": 249441.0
    },
    {
      "Item1": "2020-12-06T00:00:00",
      "Item2": 252765.0
    },
    {
      "Item1": "2020-12-07T00:00:00",
      "Item2": 256811.0
    },
    {
      "Item1": "2020-12-08T00:00:00",
      "Item2": 262314.0
    },
    {
      "Item1": "2020-12-09T00:00:00",
      "Item2": 265815.0
    },
    {
      "Item1": "2020-12-10T00:00:00",
      "Item2": 269665.0
    },
    {
      "Item1": "2020-12-11T00:00:00",
      "Item2": 273503.0
    },
    {
      "Item1": "2020-12-12T00:00:00",
      "Item2": 277883.0
    },
    {
      "Item1": "2020-12-13T00:00:00",
      "Item2": 281106.0
    },
    {
      "Item1": "2020-12-14T00:00:00",
      "Item2": 284174.0
    },
    {
      "Item1": "2020-12-15T00:00:00",
      "Item2": 287750.0
    },
    {
      "Item1": "2020-12-16T00:00:00",
      "Item2": 291042.0
    },
    {
      "Item1": "2020-12-17T00:00:00",
      "Item2": 294315.0
    },
    {
      "Item1": "2020-12-18T00:00:00",
      "Item2": 297424.0
    },
    {
      "Item1": "2020-12-19T00:00:00",
      "Item2": 300611.0
    },
    {
      "Item1": "2020-12-20T00:00:00",
      "Item2": 303213.0
    },
    {
      "Item1": "2020-12-21T00:00:00",
      "Item2": 305658.0
    },
    {
      "Item1": "2020-12-22T00:00:00",
      "Item2": 309595.0
    },
    {
      "Item1": "2020-12-23T00:00:00",
      "Item2": 312921.0
    },
    {
      "Item1": "2020-12-24T00:00:00",
      "Item2": 315952.0
    },
    {
      "Item1": "2020-12-25T00:00:00",
      "Item2": 318154.0
    },
    {
      "Item1": "2020-12-26T00:00:00",
      "Item2": 320753.0
    },
    {
      "Item1": "2020-12-27T00:00:00",
      "Item2": 323002.0
    },
    {
      "Item1": "2020-12-28T00:00:00",
      "Item2": 326768.0
    },
    {
      "Item1": "2020-12-29T00:00:00",
      "Item2": 328974.0
    },
    {
      "Item1": "2020-12-30T00:00:00",
      "Item2": 330990.0
    },
    {
      "Item1": "2020-12-31T00:00:00",
      "Item2": 332952.0
    },
    {
      "Item1": "2021-01-01T00:00:00",
      "Item2": 334901.0
    },
    {
      "Item1": "2021-01-02T00:00:00",
      "Item2": 336922.0
    },
    {
      "Item1": "2021-01-03T00:00:00",
      "Item2": 338831.0
    },
    {
      "Item1": "2021-01-04T00:00:00",
      "Item2": 340273.0
    },
    {
      "Item1": "2021-01-05T00:00:00",
      "Item2": 343039.0
    },
    {
      "Item1": "2021-01-06T00:00:00",
      "Item2": 344974.0
    },
    {
      "Item1": "2021-01-07T00:00:00",
      "Item2": 346901.0
    },
    {
      "Item1": "2021-01-08T00:00:00",
      "Item2": 349215.0
    },
    {
      "Item1": "2021-01-09T00:00:00",
      "Item2": 351382.0
    },
    {
      "Item1": "2021-01-10T00:00:00",
      "Item2": 353749.0
    },
    {
      "Item1": "2021-01-11T00:00:00",
      "Item2": 355530.0
    },
    {
      "Item1": "2021-01-12T00:00:00",
      "Item2": 357562.0
    },
    {
      "Item1": "2021-01-13T00:00:00",
      "Item2": 359692.0
    },
    {
      "Item1": "2021-01-14T00:00:00",
      "Item2": 362931.0
    },
    {
      "Item1": "2021-01-15T00:00:00",
      "Item2": 365214.0
    },
    {
      "Item1": "2021-01-16T00:00:00",
      "Item2": 367785.0
    },
    {
      "Item1": "2021-01-17T00:00:00",
      "Item2": 369218.0
    },
    {
      "Item1": "2021-01-18T00:00:00",
      "Item2": 370865.0
    },
    {
      "Item1": "2021-01-19T00:00:00",
      "Item2": 373090.0
    },
    {
      "Item1": "2021-01-20T00:00:00",
      "Item2": 374824.0
    },
    {
      "Item1": "2021-01-21T00:00:00",
      "Item2": 376360.0
    },
    {
      "Item1": "2021-01-22T00:00:00",
      "Item2": 378408.0
    },
    {
      "Item1": "2021-01-23T00:00:00",
      "Item2": 380248.0
    },
    {
      "Item1": "2021-01-24T00:00:00",
      "Item2": 381654.0
    },
    {
      "Item1": "2021-01-25T00:00:00",
      "Item2": 383200.0
    },
    {
      "Item1": "2021-01-26T00:00:00",
      "Item2": 384926.0
    },
    {
      "Item1": "2021-01-27T00:00:00",
      "Item2": 386351.0
    },
    {
      "Item1": "2021-01-28T00:00:00",
      "Item2": 387787.0
    },
    {
      "Item1": "2021-01-29T00:00:00",
      "Item2": 389476.0
    },
    {
      "Item1": "2021-01-30T00:00:00",
      "Item2": 391076.0
    },
    {
      "Item1": "2021-01-31T00:00:00",
      "Item2": 392497.0
    },
    {
      "Item1": "2021-02-01T00:00:00",
      "Item2": 393747.0
    },
    {
      "Item1": "2021-02-02T00:00:00",
      "Item2": 395316.0
    },
    {
      "Item1": "2021-02-03T00:00:00",
      "Item2": 396709.0
    },
    {
      "Item1": "2021-02-04T00:00:00",
      "Item2": 397910.0
    },
    {
      "Item1": "2021-02-05T00:00:00",
      "Item2": 399329.0
    },
    {
      "Item1": "2021-02-06T00:00:00",
      "Item2": 400851.0
    },
    {
      "Item1": "2021-02-07T00:00:00",
      "Item2": 402053.0
    },
    {
      "Item1": "2021-02-08T00:00:00",
      "Item2": 403302.0
    },
    {
      "Item1": "2021-02-09T00:00:00",
      "Item2": 404676.0
    },
    {
      "Item1": "2021-02-10T00:00:00",
      "Item2": 405921.0
    },
    {
      "Item1": "2021-02-11T00:00:00",
      "Item2": 407155.0
    },
    {
      "Item1": "2021-02-12T00:00:00",
      "Item2": 408426.0
    },
    {
      "Item1": "2021-02-13T00:00:00",
      "Item2": 409877.0
    },
    {
      "Item1": "2021-02-14T00:00:00",
      "Item2": 411199.0
    },
    {
      "Item1": "2021-02-15T00:00:00",
      "Item2": 412457.0
    },
    {
      "Item1": "2021-02-16T00:00:00",
      "Item2": 413908.0
    },
    {
      "Item1": "2021-02-17T00:00:00",
      "Item2": 415221.0
    },
    {
      "Item1": "2021-02-18T00:00:00",
      "Item2": 416431.0
    },
    {
      "Item1": "2021-02-19T00:00:00",
      "Item2": 417654.0
    },
    {
      "Item1": "2021-02-20T00:00:00",
      "Item2": 419283.0
    },
    {
      "Item1": "2021-02-21T00:00:00",
      "Item2": 420509.0
    },
    {
      "Item1": "2021-02-22T00:00:00",
      "Item2": 421811.0
    },
    {
      "Item1": "2021-02-23T00:00:00",
      "Item2": 423014.0
    },
    {
      "Item1": "2021-02-24T00:00:00",
      "Item2": 424348.0
    },
    {
      "Item1": "2021-02-25T00:00:00",
      "Item2": 425786.0
    },
    {
      "Item1": "2021-02-26T00:00:00",
      "Item2": 427257.0
    },
    {
      "Item1": "2021-02-27T00:00:00",
      "Item2": 428904.0
    },
    {
      "Item1": "2021-02-28T00:00:00",
      "Item2": 430415.0
    },
    {
      "Item1": "2021-03-01T00:00:00",
      "Item2": 432016.0
    },
    {
      "Item1": "2021-03-02T00:00:00",
      "Item2": 433873.0
    },
    {
      "Item1": "2021-03-03T00:00:00",
      "Item2": 435669.0
    },
    {
      "Item1": "2021-03-04T00:00:00",
      "Item2": 437202.0
    },
    {
      "Item1": "2021-03-05T00:00:00",
      "Item2": 439101.0
    },
    {
      "Item1": "2021-03-06T00:00:00",
      "Item2": 441309.0
    },
    {
      "Item1": "2021-03-07T00:00:00",
      "Item2": 443152.0
    },
    {
      "Item1": "2021-03-08T00:00:00",
      "Item2": 445032.0
    },
    {
      "Item1": "2021-03-09T00:00:00",
      "Item2": 447041.0
    },
    {
      "Item1": "2021-03-10T00:00:00",
      "Item2": 449053.0
    },
    {
      "Item1": "2021-03-11T00:00:00",
      "Item2": 450862.0
    },
    {
      "Item1": "2021-03-12T00:00:00",
      "Item2": 453078.0
    },
    {
      "Item1": "2021-03-13T00:00:00",
      "Item2": 455271.0
    },
    {
      "Item1": "2021-03-14T00:00:00",
      "Item2": 457266.0
    },
    {
      "Item1": "2021-03-15T00:00:00",
      "Item2": 459288.0
    },
    {
      "Item1": "2021-03-16T00:00:00",
      "Item2": 461659.0
    },
    {
      "Item1": "2021-03-17T00:00:00",
      "Item2": 463714.0
    },
    {
      "Item1": "2021-03-18T00:00:00",
      "Item2": 465984.0
    },
    {
      "Item1": "2021-03-19T00:00:00",
      "Item2": 468275.0
    },
    {
      "Item1": "2021-03-20T00:00:00",
      "Item2": 470684.0
    },
    {
      "Item1": "2021-03-21T00:00:00",
      "Item2": 473357.0
    },
    {
      "Item1": "2021-03-22T00:00:00",
      "Item2": 475227.0
    },
    {
      "Item1": "2021-03-23T00:00:00",
      "Item2": 477940.0
    },
    {
      "Item1": "2021-03-24T00:00:00",
      "Item2": 480597.0
    },
    {
      "Item1": "2021-03-25T00:00:00",
      "Item2": 483460.0
    },
    {
      "Item1": "2021-03-26T00:00:00",
      "Item2": 486088.0
    },
    {
      "Item1": "2021-03-27T00:00:00",
      "Item2": 488964.0
    },
    {
      "Item1": "2021-03-28T00:00:00",
      "Item2": 491619.0
    },
    {
      "Item1": "2021-03-29T00:00:00",
      "Item2": 494377.0
    },
    {
      "Item1": "2021-03-30T00:00:00",
      "Item2": 497816.0
    },
    {
      "Item1": "2021-03-31T00:00:00",
      "Item2": 501116.0
    },
    {
      "Item1": "2021-04-01T00:00:00",
      "Item2": 503729.0
    },
    {
      "Item1": "2021-04-02T00:00:00",
      "Item2": 506675.0
    },
    {
      "Item1": "2021-04-03T00:00:00",
      "Item2": 509550.0
    },
    {
      "Item1": "2021-04-04T00:00:00",
      "Item2": 512642.0
    },
    {
      "Item1": "2021-04-05T00:00:00",
      "Item2": 516084.0
    },
    {
      "Item1": "2021-04-06T00:00:00",
      "Item2": 519202.0
    },
    {
      "Item1": "2021-04-07T00:00:00",
      "Item2": 522774.0
    },
    {
      "Item1": "2021-04-08T00:00:00",
      "Item2": 525682.0
    },
    {
      "Item1": "2021-04-09T00:00:00",
      "Item2": 529191.0
    },
    {
      "Item1": "2021-04-10T00:00:00",
      "Item2": 532539.0
    },
    {
      "Item1": "2021-04-11T00:00:00",
      "Item2": 535798.0
    },
    {
      "Item1": "2021-04-12T00:00:00",
      "Item2": 538609.0
    },
    {
      "Item1": "2021-04-13T00:00:00",
      "Item2": 541786.0
    },
    {
      "Item1": "2021-04-14T00:00:00",
      "Item2": 544989.0
    },
    {
      "Item1": "2021-04-15T00:00:00",
      "Item2": 547604.0
    },
    {
      "Item1": "2021-04-16T00:00:00",
      "Item2": 550470.0
    },
    {
      "Item1": "2021-04-17T00:00:00",
      "Item2": 552619.0
    },
    {
      "Item1": "2021-04-18T00:00:00",
      "Item2": 555218.0
    },
    {
      "Item1": "2021-04-19T00:00:00",
      "Item2": 557467.0
    },
    {
      "Item1": "2021-04-20T00:00:00",
      "Item2": 560492.0
    },
    {
      "Item1": "2021-04-21T00:00:00",
      "Item2": 563256.0
    },
    {
      "Item1": "2021-04-22T00:00:00",
      "Item2": 565513.0
    },
    {
      "Item1": "2021-04-23T00:00:00",
      "Item2": 568213.0
    },
    {
      "Item1": "2021-04-24T00:00:00",
      "Item2": 570684.0
    },
    {
      "Item1": "2021-04-25T00:00:00",
      "Item2": 573155.0
    },
    {
      "Item1": "2021-04-26T00:00:00",
      "Item2": 575217.0
    },
    {
      "Item1": "2021-04-27T00:00:00",
      "Item2": 577977.0
    },
    {
      "Item1": "2021-04-28T00:00:00",
      "Item2": 580330.0
    },
    {
      "Item1": "2021-04-29T00:00:00",
      "Item2": 582575.0
    },
    {
      "Item1": "2021-04-30T00:00:00",
      "Item2": 584777.0
    },
    {
      "Item1": "2021-05-01T00:00:00",
      "Item2": 587115.0
    },
    {
      "Item1": "2021-05-02T00:00:00",
      "Item2": 589534.0
    },
    {
      "Item1": "2021-05-03T00:00:00",
      "Item2": 591525.0
    },
    {
      "Item1": "2021-05-04T00:00:00",
      "Item2": 593684.0
    },
    {
      "Item1": "2021-05-05T00:00:00",
      "Item2": 595877.0
    },
    {
      "Item1": "2021-05-06T00:00:00",
      "Item2": 597922.0
    },
    {
      "Item1": "2021-05-07T00:00:00",
      "Item2": 599854.0
    },
    {
      "Item1": "2021-05-08T00:00:00",
      "Item2": 601958.0
    },
    {
      "Item1": "2021-05-09T00:00:00",
      "Item2": 603901.0
    },
    {
      "Item1": "2021-05-10T00:00:00",
      "Item2": 605441.0
    },
    {
      "Item1": "2021-05-11T00:00:00",
      "Item2": 607712.0
    },
    {
      "Item1": "2021-05-12T00:00:00",
      "Item2": 609666.0
    },
    {
      "Item1": "2021-05-13T00:00:00",
      "Item2": 611254.0
    },
    {
      "Item1": "2021-05-14T00:00:00",
      "Item2": 612523.0
    },
    {
      "Item1": "2021-05-15T00:00:00",
      "Item2": 614803.0
    },
    {
      "Item1": "2021-05-16T00:00:00",
      "Item2": 616148.0
    },
    {
      "Item1": "2021-05-17T00:00:00",
      "Item2": 617307.0
    },
    {
      "Item1": "2021-05-18T00:00:00",
      "Item2": 618798.0
    },
    {
      "Item1": "2021-05-19T00:00:00",
      "Item2": 618798.0
    },
    {
      "Item1": "2021-05-20T00:00:00",
      "Item2": 619756.0
    },
    {
      "Item1": "2021-05-21T00:00:00",
      "Item2": 620837.0
    },
    {
      "Item1": "2021-05-22T00:00:00",
      "Item2": 621998.0
    },
    {
      "Item1": "2021-05-23T00:00:00",
      "Item2": 622889.0
    },
    {
      "Item1": "2021-05-24T00:00:00",
      "Item2": 623668.0
    },
    {
      "Item1": "2021-05-25T00:00:00",
      "Item2": 624549.0
    },
    {
      "Item1": "2021-05-26T00:00:00",
      "Item2": 625453.0
    },
    {
      "Item1": "2021-05-27T00:00:00",
      "Item2": 626259.0
    },
    {
      "Item1": "2021-05-28T00:00:00",
      "Item2": 626815.0
    },
    {
      "Item1": "2021-05-29T00:00:00",
      "Item2": 627672.0
    },
    {
      "Item1": "2021-05-30T00:00:00",
      "Item2": 628312.0
    },
    {
      "Item1": "2021-05-31T00:00:00",
      "Item2": 628856.0
    },
    {
      "Item1": "2021-06-01T00:00:00",
      "Item2": 629713.0
    },
    {
      "Item1": "2021-06-02T00:00:00",
      "Item2": 630274.0
    },
    {
      "Item1": "2021-06-03T00:00:00",
      "Item2": 630731.0
    },
    {
      "Item1": "2021-06-04T00:00:00",
      "Item2": 631138.0
    },
    {
      "Item1": "2021-06-05T00:00:00",
      "Item2": 630458.0
    },
    {
      "Item1": "2021-06-06T00:00:00",
      "Item2": 630942.0
    },
    {
      "Item1": "2021-06-07T00:00:00",
      "Item2": 631294.0
    },
    {
      "Item1": "2021-06-08T00:00:00",
      "Item2": 631869.0
    },
    {
      "Item1": "2021-06-09T00:00:00",
      "Item2": 632188.0
    },
    {
      "Item1": "2021-06-10T00:00:00",
      "Item2": 632660.0
    },
    {
      "Item1": "2021-06-11T00:00:00",
      "Item2": 633105.0
    },
    {
      "Item1": "2021-06-12T00:00:00",
      "Item2": 633538.0
    },
    {
      "Item1": "2021-06-13T00:00:00",
      "Item2": 633939.0
    },
    {
      "Item1": "2021-06-14T00:00:00",
      "Item2": 634123.0
    },
    {
      "Item1": "2021-06-15T00:00:00",
      "Item2": 634439.0
    },
    {
      "Item1": "2021-06-16T00:00:00",
      "Item2": 634900.0
    },
    {
      "Item1": "2021-06-17T00:00:00",
      "Item2": 635192.0
    },
    {
      "Item1": "2021-06-18T00:00:00",
      "Item2": 635544.0
    },
    {
      "Item1": "2021-06-19T00:00:00",
      "Item2": 635886.0
    },
    {
      "Item1": "2021-06-20T00:00:00",
      "Item2": 636125.0
    },
    {
      "Item1": "2021-06-21T00:00:00",
      "Item2": 636365.0
    },
    {
      "Item1": "2021-06-22T00:00:00",
      "Item2": 636523.0
    },
    {
      "Item1": "2021-06-23T00:00:00",
      "Item2": 636740.0
    },
    {
      "Item1": "2021-06-24T00:00:00",
      "Item2": 636923.0
    },
    {
      "Item1": "2021-06-25T00:00:00",
      "Item2": 637051.0
    },
    {
      "Item1": "2021-06-26T00:00:00",
      "Item2": 637238.0
    },
    {
      "Item1": "2021-06-27T00:00:00",
      "Item2": 637424.0
    },
    {
      "Item1": "2021-06-28T00:00:00",
      "Item2": 637545.0
    },
    {
      "Item1": "2021-06-29T00:00:00",
      "Item2": 637613.0
    },
    {
      "Item1": "2021-06-30T00:00:00",
      "Item2": 637751.0
    },
    {
      "Item1": "2021-07-01T00:00:00",
      "Item2": 637909.0
    },
    {
      "Item1": "2021-07-02T00:00:00",
      "Item2": 638032.0
    },
    {
      "Item1": "2021-07-03T00:00:00",
      "Item2": 638167.0
    },
    {
      "Item1": "2021-07-04T00:00:00",
      "Item2": 638319.0
    },
    {
      "Item1": "2021-07-05T00:00:00",
      "Item2": 638378.0
    },
    {
      "Item1": "2021-07-06T00:00:00",
      "Item2": 638456.0
    },
    {
      "Item1": "2021-07-07T00:00:00",
      "Item2": 638566.0
    },
    {
      "Item1": "2021-07-08T00:00:00",
      "Item2": 638618.0
    },
    {
      "Item1": "2021-07-09T00:00:00",
      "Item2": 638719.0
    },
    {
      "Item1": "2021-07-10T00:00:00",
      "Item2": 638814.0
    },
    {
      "Item1": "2021-07-11T00:00:00",
      "Item2": 638889.0
    },
    {
      "Item1": "2021-07-12T00:00:00",
      "Item2": 638965.0
    },
    {
      "Item1": "2021-07-13T00:00:00",
      "Item2": 639035.0
    },
    {
      "Item1": "2021-07-14T00:00:00",
      "Item2": 639154.0
    },
    {
      "Item1": "2021-07-15T00:00:00",
      "Item2": 639239.0
    },
    {
      "Item1": "2021-07-16T00:00:00",
      "Item2": 639352.0
    },
    {
      "Item1": "2021-07-17T00:00:00",
      "Item2": 639422.0
    },
    {
      "Item1": "2021-07-18T00:00:00",
      "Item2": 639573.0
    },
    {
      "Item1": "2021-07-19T00:00:00",
      "Item2": 639700.0
    },
    {
      "Item1": "2021-07-20T00:00:00",
      "Item2": 639831.0
    },
    {
      "Item1": "2021-07-21T00:00:00",
      "Item2": 640018.0
    },
    {
      "Item1": "2021-07-22T00:00:00",
      "Item2": 640202.0
    },
    {
      "Item1": "2021-07-23T00:00:00",
      "Item2": 640430.0
    },
    {
      "Item1": "2021-07-24T00:00:00",
      "Item2": 640685.0
    },
    {
      "Item1": "2021-07-25T00:00:00",
      "Item2": 640951.0
    },
    {
      "Item1": "2021-07-26T00:00:00",
      "Item2": 641222.0
    },
    {
      "Item1": "2021-07-27T00:00:00",
      "Item2": 641541.0
    },
    {
      "Item1": "2021-07-28T00:00:00",
      "Item2": 641880.0
    },
    {
      "Item1": "2021-07-29T00:00:00",
      "Item2": 642229.0
    },
    {
      "Item1": "2021-07-30T00:00:00",
      "Item2": 642597.0
    },
    {
      "Item1": "2021-07-31T00:00:00",
      "Item2": 643027.0
    },
    {
      "Item1": "2021-08-01T00:00:00",
      "Item2": 643387.0
    },
    {
      "Item1": "2021-08-02T00:00:00",
      "Item2": 643694.0
    },
    {
      "Item1": "2021-08-03T00:00:00",
      "Item2": 644038.0
    },
    {
      "Item1": "2021-08-04T00:00:00",
      "Item2": 644388.0
    },
    {
      "Item1": "2021-08-05T00:00:00",
      "Item2": 0.0
    },
    {
      "Item1": "2021-08-06T00:00:00",
      "Item2": 0.0
    },
    {
      "Item1": "2021-08-07T00:00:00",
      "Item2": 0.0
    },
    {
      "Item1": "2021-08-08T00:00:00",
      "Item2": 0.0
    },
    {
      "Item1": "2021-08-09T00:00:00",
      "Item2": 0.0
    },
    {
      "Item1": "2021-08-10T00:00:00",
      "Item2": 0.0
    },
    {
      "Item1": "2021-08-11T00:00:00",
      "Item2": 0.0
    },
    {
      "Item1": "2021-08-12T00:00:00",
      "Item2": 0.0
    },
    {
      "Item1": "2021-08-13T00:00:00",
      "Item2": 0.0
    },
    {
      "Item1": "2021-08-14T00:00:00",
      "Item2": 0.0
    },
    {
      "Item1": "2021-08-15T00:00:00",
      "Item2": 0.0
    },
    {
      "Item1": "2021-08-16T00:00:00",
      "Item2": 0.0
    },
    {
      "Item1": "2021-08-17T00:00:00",
      "Item2": 0.0
    },
    {
      "Item1": "2021-08-18T00:00:00",
      "Item2": 0.0
    },
    {
      "Item1": "2021-08-19T00:00:00",
      "Item2": 0.0
    },
    {
      "Item1": "2021-08-20T00:00:00",
      "Item2": 0.0
    },
    {
      "Item1": "2021-08-21T00:00:00",
      "Item2": 0.0
    },
    {
      "Item1": "2021-08-22T00:00:00",
      "Item2": 0.0
    },
    {
      "Item1": "2021-08-23T00:00:00",
      "Item2": 0.0
    },
    {
      "Item1": "2021-08-24T00:00:00",
      "Item2": 0.0
    },
    {
      "Item1": "2021-08-25T00:00:00",
      "Item2": 0.0
    },
    {
      "Item1": "2021-08-26T00:00:00",
      "Item2": 0.0
    },
    {
      "Item1": "2021-08-27T00:00:00",
      "Item2": 0.0
    },
    {
      "Item1": "2021-08-28T00:00:00",
      "Item2": 0.0
    },
    {
      "Item1": "2021-08-29T00:00:00",
      "Item2": 0.0
    },
    {
      "Item1": "2021-08-30T00:00:00",
      "Item2": 0.0
    },
    {
      "Item1": "2021-08-31T00:00:00",
      "Item2": 0.0
    },
    {
      "Item1": "2021-09-01T00:00:00",
      "Item2": 0.0
    },
    {
      "Item1": "2021-09-02T00:00:00",
      "Item2": 0.0
    },
    {
      "Item1": "2021-09-03T00:00:00",
      "Item2": 0.0
    },
    {
      "Item1": "2021-09-04T00:00:00",
      "Item2": 0.0
    },
    {
      "Item1": "2021-09-05T00:00:00",
      "Item2": 0.0
    },
    {
      "Item1": "2021-09-06T00:00:00",
      "Item2": 0.0
    },
    {
      "Item1": "2021-09-07T00:00:00",
      "Item2": 0.0
    },
    {
      "Item1": "2021-09-08T00:00:00",
      "Item2": 0.0
    },
    {
      "Item1": "2021-09-09T00:00:00",
      "Item2": 0.0
    },
    {
      "Item1": "2021-09-10T00:00:00",
      "Item2": 0.0
    },
    {
      "Item1": "2021-09-11T00:00:00",
      "Item2": 0.0
    },
    {
      "Item1": "2021-09-12T00:00:00",
      "Item2": 0.0
    },
    {
      "Item1": "2021-09-13T00:00:00",
      "Item2": 0.0
    },
    {
      "Item1": "2021-09-14T00:00:00",
      "Item2": 0.0
    },
    {
      "Item1": "2021-09-15T00:00:00",
      "Item2": 0.0
    },
    {
      "Item1": "2021-09-16T00:00:00",
      "Item2": 0.0
    },
    {
      "Item1": "2021-09-17T00:00:00",
      "Item2": 0.0
    },
    {
      "Item1": "2021-09-18T00:00:00",
      "Item2": 0.0
    },
    {
      "Item1": "2021-09-19T00:00:00",
      "Item2": 0.0
    },
    {
      "Item1": "2021-09-20T00:00:00",
      "Item2": 0.0
    },
    {
      "Item1": "2021-09-21T00:00:00",
      "Item2": 0.0
    },
    {
      "Item1": "2021-09-22T00:00:00",
      "Item2": 0.0
    },
    {
      "Item1": "2021-09-23T00:00:00",
      "Item2": 0.0
    },
    {
      "Item1": "2021-09-24T00:00:00",
      "Item2": 0.0
    },
    {
      "Item1": "2021-09-25T00:00:00",
      "Item2": 0.0
    },
    {
      "Item1": "2021-09-26T00:00:00",
      "Item2": 0.0
    },
    {
      "Item1": "2021-09-27T00:00:00",
      "Item2": 0.0
    },
    {
      "Item1": "2021-09-28T00:00:00",
      "Item2": 0.0
    },
    {
      "Item1": "2021-09-29T00:00:00",
      "Item2": 0.0
    },
    {
      "Item1": "2021-09-30T00:00:00",
      "Item2": 0.0
    },
    {
      "Item1": "2021-10-01T00:00:00",
      "Item2": 0.0
    },
    {
      "Item1": "2021-10-02T00:00:00",
      "Item2": 0.0
    },
    {
      "Item1": "2021-10-03T00:00:00",
      "Item2": 0.0
    },
    {
      "Item1": "2021-10-04T00:00:00",
      "Item2": 0.0
    },
    {
      "Item1": "2021-10-05T00:00:00",
      "Item2": 0.0
    },
    {
      "Item1": "2021-10-06T00:00:00",
      "Item2": 0.0
    },
    {
      "Item1": "2021-10-07T00:00:00",
      "Item2": 0.0
    },
    {
      "Item1": "2021-10-08T00:00:00",
      "Item2": 0.0
    },
    {
      "Item1": "2021-10-09T00:00:00",
      "Item2": 0.0
    },
    {
      "Item1": "2021-10-10T00:00:00",
      "Item2": 0.0
    },
    {
      "Item1": "2021-10-11T00:00:00",
      "Item2": 0.0
    },
    {
      "Item1": "2021-10-12T00:00:00",
      "Item2": 0.0
    },
    {
      "Item1": "2021-10-13T00:00:00",
      "Item2": 0.0
    },
    {
      "Item1": "2021-10-14T00:00:00",
      "Item2": 0.0
    },
    {
      "Item1": "2021-10-15T00:00:00",
      "Item2": 0.0
    },
    {
      "Item1": "2021-10-16T00:00:00",
      "Item2": 0.0
    },
    {
      "Item1": "2021-10-17T00:00:00",
      "Item2": 0.0
    },
    {
      "Item1": "2021-10-18T00:00:00",
      "Item2": 0.0
    },
    {
      "Item1": "2021-10-19T00:00:00",
      "Item2": 0.0
    },
    {
      "Item1": "2021-10-20T00:00:00",
      "Item2": 0.0
    },
    {
      "Item1": "2021-10-21T00:00:00",
      "Item2": 0.0
    },
    {
      "Item1": "2021-10-22T00:00:00",
      "Item2": 0.0
    },
    {
      "Item1": "2021-10-23T00:00:00",
      "Item2": 0.0
    },
    {
      "Item1": "2021-10-24T00:00:00",
      "Item2": 0.0
    },
    {
      "Item1": "2021-10-25T00:00:00",
      "Item2": 0.0
    },
    {
      "Item1": "2021-10-26T00:00:00",
      "Item2": 0.0
    },
    {
      "Item1": "2021-10-27T00:00:00",
      "Item2": 0.0
    },
    {
      "Item1": "2021-10-28T00:00:00",
      "Item2": 0.0
    },
    {
      "Item1": "2021-10-29T00:00:00",
      "Item2": 0.0
    },
    {
      "Item1": "2021-10-30T00:00:00",
      "Item2": 0.0
    },
    {
      "Item1": "2021-10-31T00:00:00",
      "Item2": 0.0
    },
    {
      "Item1": "2021-11-01T00:00:00",
      "Item2": 0.0
    },
    {
      "Item1": "2021-11-02T00:00:00",
      "Item2": 0.0
    },
    {
      "Item1": "2021-11-03T00:00:00",
      "Item2": 0.0
    },
    {
      "Item1": "2021-11-04T00:00:00",
      "Item2": 0.0
    },
    {
      "Item1": "2021-11-05T00:00:00",
      "Item2": 0.0
    },
    {
      "Item1": "2021-11-06T00:00:00",
      "Item2": 0.0
    },
    {
      "Item1": "2021-11-07T00:00:00",
      "Item2": 0.0
    },
    {
      "Item1": "2021-11-08T00:00:00",
      "Item2": 0.0
    },
    {
      "Item1": "2021-11-09T00:00:00",
      "Item2": 0.0
    },
    {
      "Item1": "2021-11-10T00:00:00",
      "Item2": 0.0
    },
    {
      "Item1": "2021-11-11T00:00:00",
      "Item2": 0.0
    },
    {
      "Item1": "2021-11-12T00:00:00",
      "Item2": 0.0
    },
    {
      "Item1": "2021-11-13T00:00:00",
      "Item2": 0.0
    },
    {
      "Item1": "2021-11-14T00:00:00",
      "Item2": 0.0
    },
    {
      "Item1": "2021-11-15T00:00:00",
      "Item2": 0.0
    },
    {
      "Item1": "2021-11-16T00:00:00",
      "Item2": 0.0
    },
    {
      "Item1": "2021-11-17T00:00:00",
      "Item2": 0.0
    },
    {
      "Item1": "2021-11-18T00:00:00",
      "Item2": 0.0
    },
    {
      "Item1": "2021-11-19T00:00:00",
      "Item2": 0.0
    },
    {
      "Item1": "2021-11-20T00:00:00",
      "Item2": 0.0
    },
    {
      "Item1": "2021-11-21T00:00:00",
      "Item2": 0.0
    },
    {
      "Item1": "2021-11-22T00:00:00",
      "Item2": 0.0
    },
    {
      "Item1": "2021-11-23T00:00:00",
      "Item2": 0.0
    },
    {
      "Item1": "2021-11-24T00:00:00",
      "Item2": 0.0
    },
    {
      "Item1": "2021-11-25T00:00:00",
      "Item2": 0.0
    },
    {
      "Item1": "2021-11-26T00:00:00",
      "Item2": 0.0
    },
    {
      "Item1": "2021-11-27T00:00:00",
      "Item2": 0.0
    },
    {
      "Item1": "2021-11-28T00:00:00",
      "Item2": 0.0
    },
    {
      "Item1": "2021-11-29T00:00:00",
      "Item2": 0.0
    },
    {
      "Item1": "2021-11-30T00:00:00",
      "Item2": 0.0
    },
    {
      "Item1": "2021-12-01T00:00:00",
      "Item2": 0.0
    },
    {
      "Item1": "2021-12-02T00:00:00",
      "Item2": 0.0
    },
    {
      "Item1": "2021-12-03T00:00:00",
      "Item2": 0.0
    },
    {
      "Item1": "2021-12-04T00:00:00",
      "Item2": 0.0
    },
    {
      "Item1": "2021-12-05T00:00:00",
      "Item2": 0.0
    },
    {
      "Item1": "2021-12-06T00:00:00",
      "Item2": 0.0
    },
    {
      "Item1": "2021-12-07T00:00:00",
      "Item2": 0.0
    },
    {
      "Item1": "2021-12-08T00:00:00",
      "Item2": 0.0
    },
    {
      "Item1": "2021-12-09T00:00:00",
      "Item2": 0.0
    },
    {
      "Item1": "2021-12-10T00:00:00",
      "Item2": 0.0
    },
    {
      "Item1": "2021-12-11T00:00:00",
      "Item2": 0.0
    },
    {
      "Item1": "2021-12-12T00:00:00",
      "Item2": 0.0
    },
    {
      "Item1": "2021-12-13T00:00:00",
      "Item2": 0.0
    },
    {
      "Item1": "2021-12-14T00:00:00",
      "Item2": 0.0
    },
    {
      "Item1": "2021-12-15T00:00:00",
      "Item2": 0.0
    },
    {
      "Item1": "2021-12-16T00:00:00",
      "Item2": 0.0
    },
    {
      "Item1": "2021-12-17T00:00:00",
      "Item2": 0.0
    },
    {
      "Item1": "2021-12-18T00:00:00",
      "Item2": 0.0
    },
    {
      "Item1": "2021-12-19T00:00:00",
      "Item2": 0.0
    },
    {
      "Item1": "2021-12-20T00:00:00",
      "Item2": 0.0
    },
    {
      "Item1": "2021-12-21T00:00:00",
      "Item2": 0.0
    },
    {
      "Item1": "2021-12-22T00:00:00",
      "Item2": 0.0
    },
    {
      "Item1": "2021-12-23T00:00:00",
      "Item2": 0.0
    },
    {
      "Item1": "2021-12-24T00:00:00",
      "Item2": 0.0
    },
    {
      "Item1": "2021-12-25T00:00:00",
      "Item2": 0.0
    },
    {
      "Item1": "2021-12-26T00:00:00",
      "Item2": 0.0
    },
    {
      "Item1": "2021-12-27T00:00:00",
      "Item2": 0.0
    },
    {
      "Item1": "2021-12-28T00:00:00",
      "Item2": 0.0
    },
    {
      "Item1": "2021-12-29T00:00:00",
      "Item2": 0.0
    },
    {
      "Item1": "2021-12-30T00:00:00",
      "Item2": 0.0
    },
    {
      "Item1": "2021-12-31T00:00:00",
      "Item2": 0.0
    },
    {
      "Item1": "2022-01-01T00:00:00",
      "Item2": 0.0
    },
    {
      "Item1": "2022-01-02T00:00:00",
      "Item2": 0.0
    },
    {
      "Item1": "2022-01-03T00:00:00",
      "Item2": 0.0
    },
    {
      "Item1": "2022-01-04T00:00:00",
      "Item2": 0.0
    },
    {
      "Item1": "2022-01-05T00:00:00",
      "Item2": 0.0
    },
    {
      "Item1": "2022-01-06T00:00:00",
      "Item2": 0.0
    },
    {
      "Item1": "2022-01-07T00:00:00",
      "Item2": 0.0
    },
    {
      "Item1": "2022-01-08T00:00:00",
      "Item2": 0.0
    },
    {
      "Item1": "2022-01-09T00:00:00",
      "Item2": 0.0
    },
    {
      "Item1": "2022-01-10T00:00:00",
      "Item2": 0.0
    },
    {
      "Item1": "2022-01-11T00:00:00",
      "Item2": 0.0
    },
    {
      "Item1": "2022-01-12T00:00:00",
      "Item2": 0.0
    },
    {
      "Item1": "2022-01-13T00:00:00",
      "Item2": 0.0
    },
    {
      "Item1": "2022-01-14T00:00:00",
      "Item2": 0.0
    },
    {
      "Item1": "2022-01-15T00:00:00",
      "Item2": 0.0
    },
    {
      "Item1": "2022-01-16T00:00:00",
      "Item2": 0.0
    },
    {
      "Item1": "2022-01-17T00:00:00",
      "Item2": 0.0
    },
    {
      "Item1": "2022-01-18T00:00:00",
      "Item2": 0.0
    },
    {
      "Item1": "2022-01-19T00:00:00",
      "Item2": 0.0
    },
    {
      "Item1": "2022-01-20T00:00:00",
      "Item2": 0.0
    },
    {
      "Item1": "2022-01-21T00:00:00",
      "Item2": 0.0
    },
    {
      "Item1": "2022-01-22T00:00:00",
      "Item2": 0.0
    },
    {
      "Item1": "2022-01-23T00:00:00",
      "Item2": 0.0
    },
    {
      "Item1": "2022-01-24T00:00:00",
      "Item2": 0.0
    },
    {
      "Item1": "2022-01-25T00:00:00",
      "Item2": 0.0
    },
    {
      "Item1": "2022-01-26T00:00:00",
      "Item2": 0.0
    },
    {
      "Item1": "2022-01-27T00:00:00",
      "Item2": 0.0
    },
    {
      "Item1": "2022-01-28T00:00:00",
      "Item2": 0.0
    },
    {
      "Item1": "2022-01-29T00:00:00",
      "Item2": 0.0
    },
    {
      "Item1": "2022-01-30T00:00:00",
      "Item2": 0.0
    },
    {
      "Item1": "2022-01-31T00:00:00",
      "Item2": 0.0
    },
    {
      "Item1": "2022-02-01T00:00:00",
      "Item2": 0.0
    },
    {
      "Item1": "2022-02-02T00:00:00",
      "Item2": 0.0
    },
    {
      "Item1": "2022-02-03T00:00:00",
      "Item2": 0.0
    },
    {
      "Item1": "2022-02-04T00:00:00",
      "Item2": 0.0
    },
    {
      "Item1": "2022-02-05T00:00:00",
      "Item2": 0.0
    },
    {
      "Item1": "2022-02-06T00:00:00",
      "Item2": 0.0
    },
    {
      "Item1": "2022-02-07T00:00:00",
      "Item2": 0.0
    },
    {
      "Item1": "2022-02-08T00:00:00",
      "Item2": 0.0
    },
    {
      "Item1": "2022-02-09T00:00:00",
      "Item2": 0.0
    },
    {
      "Item1": "2022-02-10T00:00:00",
      "Item2": 0.0
    },
    {
      "Item1": "2022-02-11T00:00:00",
      "Item2": 0.0
    },
    {
      "Item1": "2022-02-12T00:00:00",
      "Item2": 0.0
    },
    {
      "Item1": "2022-02-13T00:00:00",
      "Item2": 0.0
    },
    {
      "Item1": "2022-02-14T00:00:00",
      "Item2": 0.0
    },
    {
      "Item1": "2022-02-15T00:00:00",
      "Item2": 0.0
    },
    {
      "Item1": "2022-02-16T00:00:00",
      "Item2": 0.0
    },
    {
      "Item1": "2022-02-17T00:00:00",
      "Item2": 0.0
    },
    {
      "Item1": "2022-02-18T00:00:00",
      "Item2": 0.0
    },
    {
      "Item1": "2022-02-19T00:00:00",
      "Item2": 0.0
    },
    {
      "Item1": "2022-02-20T00:00:00",
      "Item2": 0.0
    },
    {
      "Item1": "2022-02-21T00:00:00",
      "Item2": 0.0
    }
  ]
}
